api/__init__.py
api/path.py
api_utils/__init__.py
api_utils/path.py
apiu/__init__.py
apiu/path.py
path/__init__.py
api_utils-2019.9.18.dist-info/LICENSE
api_utils-2019.9.18.dist-info/METADATA
api_utils-2019.9.18.dist-info/WHEEL
api_utils-2019.9.18.dist-info/top_level.txt
api_utils-2019.9.18.dist-info/RECORD
