Metadata-Version: 2.1
Name: api-utils
Version: 2019.9.18
Summary: API utils simplify life when creating or consuming APIs
Home-page: https://pypi.org/project/api-utils/
License: UNKNOWN
Platform: UNKNOWN
Classifier: Programming Language :: Python :: 3
Classifier: License :: OSI Approved :: GNU General Public License v3 (GPLv3)
Classifier: Operating System :: OS Independent
Requires-Python: >=3.6
